{
    "color": {
        "white": {
            "value": "#ffffff"
        },
        "black": {
            "value": "#000000"
        },
        "blue": {
            "50": {
                "value": "#eff6ff"
            },
            "100": {
                "value": "#dbeafe"
            },
            "500": {
                "value": "#3b82f6"
            },
            "600": {
                "value": "#2563eb"
            },
            "700": {
                "value": "#1d4ed8"
            }
        },
        "gray": {
            "50": {
                "value": "#f9fafb"
            },
            "100": {
                "value": "#f3f4f6"
            },
            "200": {
                "value": "#e5e7eb"
            },
            "300": {
                "value": "#d1d5db"
            },
            "400": {
                "value": "#9ca3af"
            },
            "500": {
                "value": "#6b7280"
            },
            "600": {
                "value": "#4b5563"
            },
            "700": {
                "value": "#374151"
            }
        }
    },
    "spacing": {
        "xs": {
            "value": "4px"
        },
        "sm": {
            "value": "8px"
        },
        "md": {
            "value": "16px"
        },
        "lg": {
            "value": "24px"
        },
        "xl": {
            "value": "32px"
        }
    },
    "border": {
        "radius": {
            "sm": {
                "value": "4px"
            },
            "md": {
                "value": "6px"
            },
            "lg": {
                "value": "8px"
            }
        }
    }
}